.hgignore
.project
.pydevproject
MANIFEST.in
README.txt
bootstrap.py
buildout.cfg
setup.py
bin/buildout
docs/HISTORY.txt
docs/README.txt
src/ztfy/__init__.py
src/ztfy.comment.egg-info/PKG-INFO
src/ztfy.comment.egg-info/SOURCES.txt
src/ztfy.comment.egg-info/dependency_links.txt
src/ztfy.comment.egg-info/entry_points.txt
src/ztfy.comment.egg-info/namespace_packages.txt
src/ztfy.comment.egg-info/not-zip-safe
src/ztfy.comment.egg-info/requires.txt
src/ztfy.comment.egg-info/top_level.txt
src/ztfy/comment/README.txt
src/ztfy/comment/__init__.py
src/ztfy/comment/comment.py
src/ztfy/comment/configure.zcml
src/ztfy/comment/interfaces.py
src/ztfy/comment/schema.py
src/ztfy/comment/browser/__init__.py
src/ztfy/comment/browser/configure.zcml
src/ztfy/comment/doctests/README.txt
src/ztfy/comment/locales/ztfy.comment.pot
src/ztfy/comment/locales/en/LC_MESSAGES/ztfy.comment.mo
src/ztfy/comment/locales/en/LC_MESSAGES/ztfy.comment.po
src/ztfy/comment/locales/fr/LC_MESSAGES/ztfy.comment.mo
src/ztfy/comment/locales/fr/LC_MESSAGES/ztfy.comment.po
src/ztfy/comment/tests/__init__.py
src/ztfy/comment/tests/test_commentdocs.py
src/ztfy/comment/tests/test_commentdocstrings.py